sncscan.py
sncscan-1.0.1.dist-info/LICENSE
sncscan-1.0.1.dist-info/METADATA
sncscan-1.0.1.dist-info/WHEEL
sncscan-1.0.1.dist-info/entry_points.txt
sncscan-1.0.1.dist-info/top_level.txt
sncscan-1.0.1.dist-info/RECORD
