Metadata-Version: 2.1
Name: sncscan
Version: 1.0.1
Summary: sncscan: Tool for analyzing SAP Secure Network Communications (SNC).
Home-page: https://github.com/usdAG/sncscan
Author: Jonas Wamsler, Nicolas Schickert
Author-email: jonas.wamsler@usd.de
License: GPLv3
License-File: LICENSE
